<?xml version="1.0" encoding="UTF-8" ?><tv date="20260714">
<channel id="AnimexHIDIVE.us"><display-name>ANIME x HIDIVE</display-name><icon src="https://i.imgur.com/v0BlxCa.png"/></channel>
<channel id="ArirangTV.kr"><display-name>Arirang</display-name><icon src="https://i.imgur.com/Asu5pE9.png"/></channel>
<channel id="AsianCrush.us"><display-name>AsianCrush</display-name><icon src="https://i.imgur.com/hW6z1RG.png"/></channel>
<channel id="BBCNews.uk"><display-name>BBC News (North America)</display-name><icon src="https://dtil.tmsimg.com/assets/s158142_ld_h15_aa.png?lock=720x540"/></channel>
<channel id="BloombergTV.us"><display-name>Bloomberg Television</display-name><icon src="https://i.imgur.com/OuogLHx.png"/></channel>
<channel id="CBSNewsNewYork.us"><display-name>CBS News New York</display-name><icon src="https://i.imgur.com/bpc4v0u.png"/></channel>
<channel id="CCTV3.cn"><display-name>CCTV 3</display-name><icon src="https://i.imgur.com/iFlkIuw.png"/></channel>
<channel id="CNAOriginals.sg"><display-name>CNA Originals</display-name><icon src="https://i.imgur.com/hlFQTrB.png"/></channel>
<channel id="CNBCIndonesia.id"><display-name>CNBC Indonesia</display-name><icon src="https://upload.wikimedia.org/wikipedia/commons/5/51/CNBC_Indonesia_2025.svg"/></channel>
<channel id="CNBCWorld.us"><display-name>CNBC World</display-name><icon src="https://upload.wikimedia.org/wikipedia/commons/e/ee/CNBC_World_2025.svg"/></channel>
<channel id="DW.de"><display-name>DW English OTA</display-name><icon src="https://i.imgur.com/8MRNFb9.png"/></channel>
<channel id="EuronewsEnglish.fr"><display-name>Euronews</display-name><icon src="https://a.jsrdn.com/hls/22886/euronews/extras/1080_logo.png"/></channel>
<channel id="France24.fr"><display-name>France24</display-name><icon src="https://dtil.tmsimg.com/assets/s159111_ld_h15_aa.png?lock=720x540"/></channel>
<channel id="Friday.ru"><display-name>Пятница!</display-name><icon src="https://antifriz.tv/storage/images/pack_logos/71e74d77d2a9f55f496870623e5f7203.png"/></channel>
<channel id="History.us"><display-name>History East</display-name><icon src="https://upload.wikimedia.org/wikipedia/commons/thumb/0/01/History_%282021%29.svg/500px-History_%282021%29.svg.png"/></channel>
<channel id="INFAST.nl"><display-name>INFAST</display-name><icon src="https://cdn.uc.assets.prezly.com/1b9c9500-cb43-449b-9eb6-9579640ec904/InFast_portrait-red.png"/></channel>
<channel id="MTV.us"><display-name>MTV East</display-name><icon src="https://upload.wikimedia.org/wikipedia/commons/thumb/6/68/MTV_2021_%28brand_version%29.svg/960px-MTV_2021_%28brand_version%29.svg.png"/></channel>
<channel id="NHKWorldJapan.jp"><display-name>NHK World</display-name><icon src="https://jiotvimages.cdn.jio.com/dare_images/images/NHK_World_Japan.png"/></channel>
<channel id="NationalGeographic.gr"><display-name>National Geographic HD</display-name><icon src="https://upload.wikimedia.org/wikipedia/commons/thumb/f/fc/Natgeologo.svg/960px-Natgeologo.svg.png"/></channel>
<channel id="RussiaK.ru"><display-name>Культура</display-name><icon src="https://upload.wikimedia.org/wikipedia/commons/thumb/4/45/Russia-Cultura.svg/960px-Russia-Cultura.svg.png"/></channel>
<channel id="YahooFinance.us"><display-name>Yahoo Finance</display-name><icon src="https://i.imgur.com/43oHsHL.png"/></channel>
<programme start="20260713170000 +0000" stop="20260713180000 +0000" channel="ArirangTV.kr"><title lang="id">Performarts Reload:Ntok</title></programme>
<programme start="20260713180000 +0000" stop="20260713183000 +0000" channel="ArirangTV.kr"><title lang="id">K-Culture Dive</title></programme>
<programme start="20260713183000 +0000" stop="20260713190000 +0000" channel="ArirangTV.kr"><title lang="id">SMEs on The Rise 2026</title></programme>
<programme start="20260713190000 +0000" stop="20260713193000 +0000" channel="ArirangTV.kr"><title lang="id">Within The Frame</title></programme>
<programme start="20260713193000 +0000" stop="20260713195000 +0000" channel="ArirangTV.kr"><title lang="id">K-Culture Minutes: K-Now</title></programme>
<programme start="20260713195000 +0000" stop="20260713200000 +0000" channel="ArirangTV.kr"><title lang="id">K-Chat: Conversing In Korean</title></programme>
<programme start="20260713200000 +0000" stop="20260713203000 +0000" channel="ArirangTV.kr"><title lang="id">K-Food Class</title></programme>
<programme start="20260713203000 +0000" stop="20260713205000 +0000" channel="ArirangTV.kr"><title lang="id">The Grand Heritage K-ASMR</title></programme>
<programme start="20260713205000 +0000" stop="20260713210000 +0000" channel="ArirangTV.kr"><title lang="id">The Grand Heritage</title></programme>
<programme start="20260713210000 +0000" stop="20260713220000 +0000" channel="ArirangTV.kr"><title lang="id">Performarts Reload:Ntok</title></programme>
<programme start="20260713220000 +0000" stop="20260713223000 +0000" channel="ArirangTV.kr"><title lang="id">With Science, We Live</title></programme>
<programme start="20260713223000 +0000" stop="20260713225000 +0000" channel="ArirangTV.kr"><title lang="id">K-Arts Artists</title></programme>
<programme start="20260713225000 +0000" stop="20260713230000 +0000" channel="ArirangTV.kr"><title lang="id">Heritage Walks With Little Friend</title></programme>
<programme start="20260713230000 +0000" stop="20260713232000 +0000" channel="ArirangTV.kr"><title lang="id">Drawing Diary</title></programme>
<programme start="20260713232000 +0000" stop="20260713233000 +0000" channel="ArirangTV.kr"><title lang="id">Exploring Korean Literature B</title></programme>
<programme start="20260713233000 +0000" stop="20260713235000 +0000" channel="ArirangTV.kr"><title lang="id">K-Culture Minutes: K-People</title></programme>
<programme start="20260713235000 +0000" stop="20260714000000 +0000" channel="ArirangTV.kr"><title lang="id">K-Chat: Conversing In Korean</title></programme>
<programme start="20260714000000 +0000" stop="20260714003000 +0000" channel="ArirangTV.kr"><title lang="id">Diplomat&apos;s Archive: Hidden Stories</title></programme>
<programme start="20260714003000 +0000" stop="20260714010000 +0000" channel="ArirangTV.kr"><title lang="id">Paris Goes K-Crazy</title></programme>
<programme start="20260714010000 +0000" stop="20260714013000 +0000" channel="ArirangTV.kr"><title lang="id">New Day At Arirang</title></programme>
<programme start="20260714013000 +0000" stop="20260714020000 +0000" channel="ArirangTV.kr"><title lang="id">News Generation</title></programme>
<programme start="20260714020000 +0000" stop="20260714030000 +0000" channel="ArirangTV.kr"><title lang="id">Culture Crunch</title></programme>
<programme start="20260714030000 +0000" stop="20260714033000 +0000" channel="ArirangTV.kr"><title lang="id">Arirang News</title></programme>
<programme start="20260714033000 +0000" stop="20260714040000 +0000" channel="ArirangTV.kr"><title lang="id">Diplomat&apos;s Archive: Hidden Stories</title></programme>
<programme start="20260714040000 +0000" stop="20260714050000 +0000" channel="ArirangTV.kr"><title lang="id">Gugak The Music Of Korea</title></programme>
<programme start="20260714050000 +0000" stop="20260714053000 +0000" channel="ArirangTV.kr"><title lang="id">K-Culture Dive</title></programme>
<programme start="20260714053000 +0000" stop="20260714060000 +0000" channel="ArirangTV.kr"><title lang="id">News Generation</title></programme>
<programme start="20260714060000 +0000" stop="20260714063000 +0000" channel="ArirangTV.kr"><title lang="id">Paris Goes K-Crazy</title></programme>
<programme start="20260714063000 +0000" stop="20260714065000 +0000" channel="ArirangTV.kr"><title lang="id">K-Culture Minutes: K-People</title></programme>
<programme start="20260714065000 +0000" stop="20260714070000 +0000" channel="ArirangTV.kr"><title lang="id">The Living Sea Of Jeju</title></programme>
<programme start="20260714070000 +0000" stop="20260714070500 +0000" channel="ArirangTV.kr"><title lang="id">AI Headline News</title></programme>
<programme start="20260714070500 +0000" stop="20260714073000 +0000" channel="ArirangTV.kr"><title lang="id">K-Arts Artists</title></programme>
<programme start="20260714073000 +0000" stop="20260714080000 +0000" channel="ArirangTV.kr"><title lang="id">Diplomat&apos;s Archive: Hidden Stories</title></programme>
<programme start="20260714080000 +0000" stop="20260714083000 +0000" channel="ArirangTV.kr"><title lang="id">The Daily Report</title></programme>
<programme start="20260714083000 +0000" stop="20260714090000 +0000" channel="ArirangTV.kr"><title lang="id">Press Perspective</title></programme>
<programme start="20260714090000 +0000" stop="20260714100000 +0000" channel="ArirangTV.kr"><title lang="id">Gugak The Music Of Korea</title></programme>
<programme start="20260714100000 +0000" stop="20260714103000 +0000" channel="ArirangTV.kr"><title lang="id">With Science, We Live</title></programme>
<programme start="20260714103000 +0000" stop="20260714105000 +0000" channel="ArirangTV.kr"><title lang="id">Drawing Diary</title></programme>
<programme start="20260714105000 +0000" stop="20260714110000 +0000" channel="ArirangTV.kr"><title lang="id">Exploring Korean Literature B</title></programme>
<programme start="20260714110000 +0000" stop="20260714113000 +0000" channel="ArirangTV.kr"><title lang="id">Newscenter</title></programme>
<programme start="20260714113000 +0000" stop="20260714120000 +0000" channel="ArirangTV.kr"><title lang="id">Within The Frame</title></programme>
<programme start="20260714120000 +0000" stop="20260714123000 +0000" channel="ArirangTV.kr"><title lang="id">K-Culture Dive</title></programme>
<programme start="20260714123000 +0000" stop="20260714125000 +0000" channel="ArirangTV.kr"><title lang="id">K-Culture Minutes: K-People</title></programme>
<programme start="20260714125000 +0000" stop="20260714130000 +0000" channel="ArirangTV.kr"><title lang="id">The Living Sea Of Jeju</title></programme>
<programme start="20260714130000 +0000" stop="20260714130500 +0000" channel="ArirangTV.kr"><title lang="id">AI Headline News</title></programme>
<programme start="20260714130500 +0000" stop="20260714133000 +0000" channel="ArirangTV.kr"><title lang="id">Korea Travelogue 5</title></programme>
<programme start="20260714133000 +0000" stop="20260714140000 +0000" channel="ArirangTV.kr"><title lang="id">Diplomat&apos;s Archive: Hidden Stories</title></programme>
<programme start="20260714140000 +0000" stop="20260714143000 +0000" channel="ArirangTV.kr"><title lang="id">Press Perspective</title></programme>
<programme start="20260714143000 +0000" stop="20260714145000 +0000" channel="ArirangTV.kr"><title lang="id">The Grand Heritage K-ASMR</title></programme>
<programme start="20260714145000 +0000" stop="20260714150000 +0000" channel="ArirangTV.kr"><title lang="id">Hanok Scene</title></programme>
<programme start="20260714150000 +0000" stop="20260714153000 +0000" channel="ArirangTV.kr"><title lang="id">News Generation</title></programme>
<programme start="20260714153000 +0000" stop="20260714155000 +0000" channel="ArirangTV.kr"><title lang="id">Drawing Diary</title></programme>
<programme start="20260714155000 +0000" stop="20260714160000 +0000" channel="ArirangTV.kr"><title lang="id">Exploring Korean Literature B</title></programme>
<programme start="20260714160000 +0000" stop="20260714162000 +0000" channel="ArirangTV.kr"><title lang="id">K-Culture Minutes: K-People</title></programme>
<programme start="20260714162000 +0000" stop="20260714163000 +0000" channel="ArirangTV.kr"><title lang="id">Exploring Korean Literature B</title></programme>
<programme start="20260714163000 +0000" stop="20260714170000 +0000" channel="ArirangTV.kr"><title lang="id">Regional Tastes: Chungcheong</title></programme>
<programme start="20260714170000 +0000" stop="20260714180000 +0000" channel="ArirangTV.kr"><title lang="id">Gugak The Music Of Korea</title></programme>
<programme start="20260714180000 +0000" stop="20260714183000 +0000" channel="ArirangTV.kr"><title lang="id">K-Culture Dive</title></programme>
<programme start="20260714183000 +0000" stop="20260714190000 +0000" channel="ArirangTV.kr"><title lang="id">Diplomat&apos;s Archive: Hidden Stories</title></programme>
<programme start="20260714190000 +0000" stop="20260714193000 +0000" channel="ArirangTV.kr"><title lang="id">Within The Frame</title></programme>
<programme start="20260714193000 +0000" stop="20260714195000 +0000" channel="ArirangTV.kr"><title lang="id">K-Culture Minutes: K-People</title></programme>
<programme start="20260714195000 +0000" stop="20260714200000 +0000" channel="ArirangTV.kr"><title lang="id">K-Chat: Conversing In Korean</title></programme>
<programme start="20260714200000 +0000" stop="20260714203000 +0000" channel="ArirangTV.kr"><title lang="id">Regional Tastes: Chungcheong</title></programme>
<programme start="20260714203000 +0000" stop="20260714205000 +0000" channel="ArirangTV.kr"><title lang="id">The Grand Heritage K-ASMR</title></programme>
<programme start="20260714205000 +0000" stop="20260714210000 +0000" channel="ArirangTV.kr"><title lang="id">Hanok Scene</title></programme>
<programme start="20260714210000 +0000" stop="20260714220000 +0000" channel="ArirangTV.kr"><title lang="id">Gugak The Music Of Korea</title></programme>
<programme start="20260714220000 +0000" stop="20260714223000 +0000" channel="ArirangTV.kr"><title lang="id">Premium Collection</title></programme>
<programme start="20260714223000 +0000" stop="20260714225000 +0000" channel="ArirangTV.kr"><title lang="id">K-Arts Artists</title></programme>
<programme start="20260714225000 +0000" stop="20260714230000 +0000" channel="ArirangTV.kr"><title lang="id">Heritage Walks With Little Friend</title></programme>
<programme start="20260714230000 +0000" stop="20260714232000 +0000" channel="ArirangTV.kr"><title lang="id">Art And The City</title></programme>
<programme start="20260714232000 +0000" stop="20260714233000 +0000" channel="ArirangTV.kr"><title lang="id">Exploring Korean Literature B</title></programme>
<programme start="20260714233000 +0000" stop="20260714235000 +0000" channel="ArirangTV.kr"><title lang="id">K-Culture Minutes: K-Story</title></programme>
<programme start="20260714235000 +0000" stop="20260715000000 +0000" channel="ArirangTV.kr"><title lang="id">K-Chat: Conversing In Korean</title></programme>
<programme start="20260715000000 +0000" stop="20260715003000 +0000" channel="ArirangTV.kr"><title lang="id">The Art Of Pairing</title></programme>
<programme start="20260715003000 +0000" stop="20260715010000 +0000" channel="ArirangTV.kr"><title lang="id">Home To Table</title></programme>
<programme start="20260715010000 +0000" stop="20260715013000 +0000" channel="ArirangTV.kr"><title lang="id">New Day At Arirang</title></programme>
<programme start="20260715013000 +0000" stop="20260715020000 +0000" channel="ArirangTV.kr"><title lang="id">News Generation</title></programme>
<programme start="20260715020000 +0000" stop="20260715030000 +0000" channel="ArirangTV.kr"><title lang="id">Culture Crunch</title></programme>
<programme start="20260715030000 +0000" stop="20260715033000 +0000" channel="ArirangTV.kr"><title lang="id">Arirang News</title></programme>
<programme start="20260715033000 +0000" stop="20260715040000 +0000" channel="ArirangTV.kr"><title lang="id">The Art Of Pairing</title></programme>
<programme start="20260715040000 +0000" stop="20260715043000 +0000" channel="ArirangTV.kr"><title lang="id">I&apos;m Live</title></programme>
<programme start="20260715043000 +0000" stop="20260715050000 +0000" channel="ArirangTV.kr"><title lang="id">K-Stage Pan</title></programme>
<programme start="20260715050000 +0000" stop="20260715053000 +0000" channel="ArirangTV.kr"><title lang="id">K-Culture Dive</title></programme>
<programme start="20260715053000 +0000" stop="20260715060000 +0000" channel="ArirangTV.kr"><title lang="id">News Generation</title></programme>
<programme start="20260715060000 +0000" stop="20260715063000 +0000" channel="ArirangTV.kr"><title lang="id">Home To Table</title></programme>
<programme start="20260715063000 +0000" stop="20260715065000 +0000" channel="ArirangTV.kr"><title lang="id">K-Culture Minutes: K-Story</title></programme>
<programme start="20260715065000 +0000" stop="20260715070000 +0000" channel="ArirangTV.kr"><title lang="id">The Living Sea Of Jeju</title></programme>
<programme start="20260715070000 +0000" stop="20260715070500 +0000" channel="ArirangTV.kr"><title lang="id">AI Headline News</title></programme>
<programme start="20260715070500 +0000" stop="20260715073000 +0000" channel="ArirangTV.kr"><title lang="id">K-Arts Artists</title></programme>
<programme start="20260715073000 +0000" stop="20260715080000 +0000" channel="ArirangTV.kr"><title lang="id">The Art Of Pairing</title></programme>
<programme start="20260715080000 +0000" stop="20260715083000 +0000" channel="ArirangTV.kr"><title lang="id">The Daily Report</title></programme>
<programme start="20260715083000 +0000" stop="20260715090000 +0000" channel="ArirangTV.kr"><title lang="id">Press Perspective</title></programme>
<programme start="20260715090000 +0000" stop="20260715093000 +0000" channel="ArirangTV.kr"><title lang="id">I&apos;m Live</title></programme>
<programme start="20260715093000 +0000" stop="20260715100000 +0000" channel="ArirangTV.kr"><title lang="id">K-Stage Pan</title></programme>
<programme start="20260715100000 +0000" stop="20260715103000 +0000" channel="ArirangTV.kr"><title lang="id">Premium Collection</title></programme>
<programme start="20260715103000 +0000" stop="20260715105000 +0000" channel="ArirangTV.kr"><title lang="id">Art And The City</title></programme>
<programme start="20260715105000 +0000" stop="20260715110000 +0000" channel="ArirangTV.kr"><title lang="id">Exploring Korean Literature B</title></programme>
<programme start="20260715110000 +0000" stop="20260715113000 +0000" channel="ArirangTV.kr"><title lang="id">Newscenter</title></programme>
<programme start="20260715113000 +0000" stop="20260715120000 +0000" channel="ArirangTV.kr"><title lang="id">Within The Frame</title></programme>
<programme start="20260715120000 +0000" stop="20260715123000 +0000" channel="ArirangTV.kr"><title lang="id">K-Culture Dive</title></programme>
<programme start="20260715123000 +0000" stop="20260715125000 +0000" channel="ArirangTV.kr"><title lang="id">K-Culture Minutes: K-Story</title></programme>
<programme start="20260715125000 +0000" stop="20260715130000 +0000" channel="ArirangTV.kr"><title lang="id">The Living Sea Of Jeju</title></programme>
<programme start="20260715130000 +0000" stop="20260715130500 +0000" channel="ArirangTV.kr"><title lang="id">AI Headline News</title></programme>
<programme start="20260715130500 +0000" stop="20260715133000 +0000" channel="ArirangTV.kr"><title lang="id">Korea Travelogue 5</title></programme>
<programme start="20260715133000 +0000" stop="20260715140000 +0000" channel="ArirangTV.kr"><title lang="id">The Art Of Pairing</title></programme>
<programme start="20260715140000 +0000" stop="20260715143000 +0000" channel="ArirangTV.kr"><title lang="id">Press Perspective</title></programme>
<programme start="20260715143000 +0000" stop="20260715145000 +0000" channel="ArirangTV.kr"><title lang="id">The Grand Heritage K-ASMR</title></programme>
<programme start="20260715145000 +0000" stop="20260715150000 +0000" channel="ArirangTV.kr"><title lang="id">Hanok Scene</title></programme>
<programme start="20260715150000 +0000" stop="20260715153000 +0000" channel="ArirangTV.kr"><title lang="id">News Generation</title></programme>
<programme start="20260715153000 +0000" stop="20260715155000 +0000" channel="ArirangTV.kr"><title lang="id">Art And The City</title></programme>
<programme start="20260715155000 +0000" stop="20260715160000 +0000" channel="ArirangTV.kr"><title lang="id">Exploring Korean Literature B</title></programme>
<programme start="20260715160000 +0000" stop="20260715163000 +0000" channel="ArirangTV.kr"><title lang="id">Premium Collection</title></programme>
<programme start="20260715163000 +0000" stop="20260715170000 +0000" channel="ArirangTV.kr"><title lang="id">Arirang Special</title></programme>
<programme start="20260714212000 +0000" stop="20260714224000 +0000" channel="AsianCrush.us"><title lang="en">Boys Over Flowers</title><desc lang="en">Perhaps feeling it&apos;s time to expose one truth, Mr. Jung leads Jun-hee to the unknown patient&apos;s bedside; at the sight of her father, Jun-hee breaks down.</desc></programme>
<programme start="20260714224000 +0000" stop="20260715000000 +0000" channel="AsianCrush.us"><title lang="en">Boys Over Flowers</title><desc lang="en">Jun-pyo asks Yumi to make the lunchbox once more, confirming that Yumi had taken credit for her lunch.</desc></programme>
<programme start="20260714210000 +0000" stop="20260714220000 +0000" channel="CBSNewsNewYork.us"><title lang="en">CBS News New York 5pm</title><desc lang="en">Evening news coverage.</desc><category lang="en">Series</category><category lang="en">News &amp;amp; Information</category><category lang="en">News</category><episode-num system="original-air-date">20260714210000 +0000</episode-num><icon src="https://images.pluto.tv/series/6a4e11de09ad9261a963c3fa/tile_1783501279339.jpg?fill=blur&amp;amp;fit=fill&amp;amp;fm=jpg&amp;amp;h=900&amp;amp;q=75&amp;amp;w=900"/></programme>
<programme start="20260714220000 +0000" stop="20260714223000 +0000" channel="CBSNewsNewYork.us"><title lang="en">CBS News New York 6pm</title><desc lang="en">Stay informed with the latest breaking news and headlines.</desc><category lang="en">Series</category><category lang="en">News &amp;amp; Information</category><category lang="en">News</category><episode-num system="original-air-date">20260714220000 +0000</episode-num><icon src="https://images.pluto.tv/series/6a4e0b78d8618839a6e3978a/tile_1783499641573.jpg?fill=blur&amp;amp;fit=fill&amp;amp;fm=jpg&amp;amp;h=900&amp;amp;q=75&amp;amp;w=900"/></programme>
<programme start="20260714223000 +0000" stop="20260714230000 +0000" channel="CBSNewsNewYork.us"><title lang="en">CBS News New York 6pm</title><desc lang="en">Stay informed with the latest breaking news and headlines.</desc><category lang="en">Series</category><category lang="en">News &amp;amp; Information</category><category lang="en">News</category><episode-num system="original-air-date">20260714223000 +0000</episode-num><icon src="https://images.pluto.tv/series/6a4e0b78d8618839a6e3978a/tile_1783499641573.jpg?fill=blur&amp;amp;fit=fill&amp;amp;fm=jpg&amp;amp;h=900&amp;amp;q=75&amp;amp;w=900"/></programme>
<programme start="20260714230000 +0000" stop="20260715000000 +0000" channel="CBSNewsNewYork.us"><title lang="en">Latest New York News &amp;amp; Headlines</title><desc lang="en">Top stories in New York.</desc><category lang="en">Series</category><category lang="en">News &amp;amp; Information</category><category lang="en">News</category><episode-num system="original-air-date">20260714230000 +0000</episode-num><icon src="https://images.pluto.tv/series/63fdc2ee2fc2340013592965/tile_1783008041145.jpg?fill=blur&amp;amp;fit=fill&amp;amp;fm=jpg&amp;amp;h=900&amp;amp;q=75&amp;amp;w=900"/></programme>
<programme start="20260715000000 +0000" stop="20260715010000 +0000" channel="CBSNewsNewYork.us"><title lang="en">CBS News New York 8 PM</title><desc lang="en">CBS News New York is hyper local news streaming 24/7... for free! It&apos;s the Tri-State area&apos;s place to get top stories, breaking news, weather, traffic and more. Check us out. We&apos;re always on.</desc><category lang="en">Series</category><category lang="en">News &amp;amp; Information</category><category lang="en">News</category><episode-num system="original-air-date">20260715000000 +0000</episode-num><icon src="https://images.pluto.tv/series/64ef4b7d445a8a0013819173/tile_1757552441473.jpg?fill=blur&amp;amp;fit=fill&amp;amp;fm=jpg&amp;amp;h=900&amp;amp;q=75&amp;amp;w=900"/></programme>
<programme start="20260715010000 +0000" stop="20260715020000 +0000" channel="CBSNewsNewYork.us"><title lang="en">CBS News New York 8 PM</title><desc lang="en">CBS News New York is hyper local news streaming 24/7... for free! It&apos;s the Tri-State area&apos;s place to get top stories, breaking news, weather, traffic and more. Check us out. We&apos;re always on.</desc><category lang="en">Series</category><category lang="en">News &amp;amp; Information</category><category lang="en">News</category><episode-num system="original-air-date">20260715010000 +0000</episode-num><icon src="https://images.pluto.tv/series/64ef4b7d445a8a0013819173/tile_1757552441473.jpg?fill=blur&amp;amp;fit=fill&amp;amp;fm=jpg&amp;amp;h=900&amp;amp;q=75&amp;amp;w=900"/></programme>
<programme start="20260715020000 +0000" stop="20260715030000 +0000" channel="CBSNewsNewYork.us"><title lang="en">Latest New York News &amp;amp; Headlines</title><desc lang="en">Top stories in New York.</desc><category lang="en">Series</category><category lang="en">News &amp;amp; Information</category><category lang="en">News</category><episode-num system="original-air-date">20260715020000 +0000</episode-num><icon src="https://images.pluto.tv/series/63fdc2ee2fc2340013592965/tile_1783008041145.jpg?fill=blur&amp;amp;fit=fill&amp;amp;fm=jpg&amp;amp;h=900&amp;amp;q=75&amp;amp;w=900"/></programme>
<programme start="20260715030000 +0000" stop="20260715033500 +0000" channel="CBSNewsNewYork.us"><title lang="en">CBS News New York 11pm</title><desc lang="en">Local news coverage.</desc><category lang="en">Series</category><category lang="en">News &amp;amp; Information</category><category lang="en">News</category><episode-num system="original-air-date">20260715030000 +0000</episode-num><icon src="https://images.pluto.tv/series/6a4e0b79d8618839a6e39a03/tile_1783499642663.jpg?fill=blur&amp;amp;fit=fill&amp;amp;fm=jpg&amp;amp;h=900&amp;amp;q=75&amp;amp;w=900"/></programme>
<programme start="20260715033500 +0000" stop="20260715040000 +0000" channel="CBSNewsNewYork.us"><title lang="en">CBS News New York 11pm</title><desc lang="en">Local news coverage.</desc><category lang="en">Series</category><category lang="en">News &amp;amp; Information</category><category lang="en">News</category><episode-num system="original-air-date">20260715033500 +0000</episode-num><icon src="https://images.pluto.tv/series/6a4e0b79d8618839a6e39a03/tile_1783499642663.jpg?fill=blur&amp;amp;fit=fill&amp;amp;fm=jpg&amp;amp;h=900&amp;amp;q=75&amp;amp;w=900"/></programme>
<programme start="20260715040000 +0000" stop="20260715050000 +0000" channel="CBSNewsNewYork.us"><title lang="en">Latest New York News &amp;amp; Headlines</title><desc lang="en">Top stories in New York.</desc><category lang="en">Series</category><category lang="en">News &amp;amp; Information</category><category lang="en">News</category><episode-num system="original-air-date">20260715040000 +0000</episode-num><icon src="https://images.pluto.tv/series/63fdc2ee2fc2340013592965/tile_1783008041145.jpg?fill=blur&amp;amp;fit=fill&amp;amp;fm=jpg&amp;amp;h=900&amp;amp;q=75&amp;amp;w=900"/></programme>
<programme start="20260715050000 +0000" stop="20260715060000 +0000" channel="CBSNewsNewYork.us"><title lang="en">Latest New York News &amp;amp; Headlines</title><desc lang="en">Top stories in New York.</desc><category lang="en">Series</category><category lang="en">News &amp;amp; Information</category><category lang="en">News</category><episode-num system="original-air-date">20260715050000 +0000</episode-num><icon src="https://images.pluto.tv/series/63fdc2ee2fc2340013592965/tile_1783008041145.jpg?fill=blur&amp;amp;fit=fill&amp;amp;fm=jpg&amp;amp;h=900&amp;amp;q=75&amp;amp;w=900"/></programme>
<programme start="20260715060000 +0000" stop="20260715070000 +0000" channel="CBSNewsNewYork.us"><title lang="en">Latest New York News &amp;amp; Headlines</title><desc lang="en">Top stories in New York.</desc><category lang="en">Series</category><category lang="en">News &amp;amp; Information</category><category lang="en">News</category><episode-num system="original-air-date">20260715060000 +0000</episode-num><icon src="https://images.pluto.tv/series/63fdc2ee2fc2340013592965/tile_1783008041145.jpg?fill=blur&amp;amp;fit=fill&amp;amp;fm=jpg&amp;amp;h=900&amp;amp;q=75&amp;amp;w=900"/></programme>
<programme start="20260715070000 +0000" stop="20260715080000 +0000" channel="CBSNewsNewYork.us"><title lang="en">Latest New York News &amp;amp; Headlines</title><desc lang="en">Top stories in New York.</desc><category lang="en">Series</category><category lang="en">News &amp;amp; Information</category><category lang="en">News</category><episode-num system="original-air-date">20260715070000 +0000</episode-num><icon src="https://images.pluto.tv/series/63fdc2ee2fc2340013592965/tile_1783008041145.jpg?fill=blur&amp;amp;fit=fill&amp;amp;fm=jpg&amp;amp;h=900&amp;amp;q=75&amp;amp;w=900"/></programme>
<programme start="20260715080000 +0000" stop="20260715083000 +0000" channel="CBSNewsNewYork.us"><title lang="en">Latest New York News &amp;amp; Headlines</title><desc lang="en">Top stories in New York.</desc><category lang="en">Series</category><category lang="en">News &amp;amp; Information</category><category lang="en">News</category><episode-num system="original-air-date">20260715080000 +0000</episode-num><icon src="https://images.pluto.tv/series/63fdc2ee2fc2340013592965/tile_1783008041145.jpg?fill=blur&amp;amp;fit=fill&amp;amp;fm=jpg&amp;amp;h=900&amp;amp;q=75&amp;amp;w=900"/></programme>
<programme start="20260715083000 +0000" stop="20260715110000 +0000" channel="CBSNewsNewYork.us"><title lang="en">CBS News New York This Morning</title><desc lang="en">Stay informed with the latest breaking news and headlines.</desc><category lang="en">Series</category><category lang="en">News &amp;amp; Information</category><category lang="en">News</category><episode-num system="original-air-date">20260715083000 +0000</episode-num><icon src="https://images.pluto.tv/series/6463232ff2a541001b729236/tile_1757552440202.jpg?fill=blur&amp;amp;fit=fill&amp;amp;fm=jpg&amp;amp;h=900&amp;amp;q=75&amp;amp;w=900"/></programme>
<programme start="20260713164255 +0000" stop="20260713172855 +0000" channel="CCTV3.cn"><title lang="zh">综艺喜乐汇-2025-482 南来北往 9/39</title></programme>
<programme start="20260713172855 +0000" stop="20260713182855 +0000" channel="CCTV3.cn"><title lang="zh">精彩音乐汇-我的爱对你说-2026-189</title></programme>
<programme start="20260713182855 +0000" stop="20260713201355 +0000" channel="CCTV3.cn"><title lang="zh">影视留声机-2025-160-经典电影欣赏《渡江侦察记》</title></programme>
<programme start="20260713201355 +0000" stop="20260713210455 +0000" channel="CCTV3.cn"><title lang="zh">远山之约（蜀山篇）-1</title></programme>
<programme start="20260713210455 +0000" stop="20260713221955 +0000" channel="CCTV3.cn"><title lang="zh">中国乡村音乐大会-一乐千年篇</title></programme>
<programme start="20260713221955 +0000" stop="20260713223955 +0000" channel="CCTV3.cn"><title lang="zh">文化十分-2026-140</title></programme>
<programme start="20260713223955 +0000" stop="20260714000040 +0000" channel="CCTV3.cn"><title lang="zh">劲舞开跳吧！-1</title></programme>
<programme start="20260714000040 +0000" stop="20260714010455 +0000" channel="CCTV3.cn"><title lang="zh">精彩音乐汇-我的爱对你说-2026-196</title></programme>
<programme start="20260714010455 +0000" stop="20260714020200 +0000" channel="CCTV3.cn"><title lang="zh">星光大道-2026-32（星光欢唱季2）</title></programme>
<programme start="20260714020200 +0000" stop="20260714032635 +0000" channel="CCTV3.cn"><title lang="zh">全民畅舞-11</title></programme>
<programme start="20260714032635 +0000" stop="20260714045130 +0000" channel="CCTV3.cn"><title lang="zh">开门大吉-2026-28</title></programme>
<programme start="20260714045130 +0000" stop="20260714050000 +0000" channel="CCTV3.cn"><title lang="zh">综艺喜乐汇-2026-1032 咏春</title></programme>
<programme start="20260714050000 +0000" stop="20260714052020 +0000" channel="CCTV3.cn"><title lang="zh">文化十分-2026-141</title></programme>
<programme start="20260714052020 +0000" stop="20260714053240 +0000" channel="CCTV3.cn"><title lang="zh">连环话-徐州烽烟</title></programme>
<programme start="20260714053240 +0000" stop="20260714073000 +0000" channel="CCTV3.cn"><title lang="zh">乐在旅途第三季-4</title></programme>
<programme start="20260714073000 +0000" stop="20260714080140 +0000" channel="CCTV3.cn"><title lang="zh">综艺喜乐汇-2024-1309</title></programme>
<programme start="20260714080140 +0000" stop="20260714081335 +0000" channel="CCTV3.cn"><title lang="zh">国家宝藏-周游季-133</title></programme>
<programme start="20260714081335 +0000" stop="20260714094020 +0000" channel="CCTV3.cn"><title lang="zh">越战越勇-2026-22</title></programme>
<programme start="20260714094020 +0000" stop="20260714103850 +0000" channel="CCTV3.cn"><title lang="zh">综艺喜乐汇-2026-552</title></programme>
<programme start="20260714103850 +0000" stop="20260714120000 +0000" channel="CCTV3.cn"><title lang="zh">开门大吉-2026-13</title></programme>
<programme start="20260714120000 +0000" stop="20260714132230 +0000" channel="CCTV3.cn"><title lang="zh">全民畅舞-12</title></programme>
<programme start="20260714132230 +0000" stop="20260714141910 +0000" channel="CCTV3.cn"><title lang="zh">综艺喜乐汇-2026-600</title></programme>
<programme start="20260714141910 +0000" stop="20260714153430 +0000" channel="CCTV3.cn"><title lang="zh">沧海运河谣-1</title></programme>
<programme start="20260714153430 +0000" stop="20260714155900 +0000" channel="CCTV3.cn"><title lang="zh">综艺喜乐汇-2025-483 南来北往10/39</title></programme>
<programme start="20260714162030 +0000" stop="20260714170630 +0000" channel="CCTV3.cn"><title lang="zh">综艺喜乐汇-2025-484 南来北往11/39</title></programme>
<programme start="20260714170630 +0000" stop="20260714175230 +0000" channel="CCTV3.cn"><title lang="zh">综艺喜乐汇-2025-485 南来北往12/39</title></programme>
<programme start="20260714175230 +0000" stop="20260714194530 +0000" channel="CCTV3.cn"><title lang="zh">影视留声机-2025-75-经典电影欣赏《智取华山》</title></programme>
<programme start="20260714194530 +0000" stop="20260714204530 +0000" channel="CCTV3.cn"><title lang="zh">精彩音乐汇-我的爱对你说-2026-181</title></programme>
<programme start="20260714204530 +0000" stop="20260714205530 +0000" channel="CCTV3.cn"><title lang="zh">国家宝藏-周游季-136</title></programme>
<programme start="20260714205530 +0000" stop="20260714221230 +0000" channel="CCTV3.cn"><title lang="zh">全民畅舞-9</title></programme>
<programme start="20260714221230 +0000" stop="20260714223240 +0000" channel="CCTV3.cn"><title lang="zh">文化十分-2026-141</title></programme>
<programme start="20260714223240 +0000" stop="20260714235855 +0000" channel="CCTV3.cn"><title lang="zh">综艺喜乐汇-2024-612</title></programme>
<programme start="20260714235855 +0000" stop="20260715010310 +0000" channel="CCTV3.cn"><title lang="zh">精彩音乐汇-我的爱对你说-2026-197</title></programme>
<programme start="20260715010310 +0000" stop="20260715020130 +0000" channel="CCTV3.cn"><title lang="zh">星光大道-2026-33（星光欢唱季3）</title></programme>
<programme start="20260715020130 +0000" stop="20260715032810 +0000" channel="CCTV3.cn"><title lang="zh">全民畅舞-12</title></programme>
<programme start="20260715032810 +0000" stop="20260715045310 +0000" channel="CCTV3.cn"><title lang="zh">越战越勇-2026-23</title></programme>
<programme start="20260715045310 +0000" stop="20260715050000 +0000" channel="CCTV3.cn"><title lang="zh">综艺喜乐汇-2026-1034 快乐小马</title></programme>
<programme start="20260715050000 +0000" stop="20260715052020 +0000" channel="CCTV3.cn"><title lang="zh">文化十分-2026-142</title></programme>
<programme start="20260715052020 +0000" stop="20260715053340 +0000" channel="CCTV3.cn"><title lang="zh">连环话-桃园结义</title></programme>
<programme start="20260715053340 +0000" stop="20260715070215 +0000" channel="CCTV3.cn"><title lang="zh">你好时光-3</title></programme>
<programme start="20260715070215 +0000" stop="20260715073815 +0000" channel="CCTV3.cn"><title lang="zh">综艺喜乐汇-2024-1090</title></programme>
<programme start="20260715073815 +0000" stop="20260715090645 +0000" channel="CCTV3.cn"><title lang="zh">星光大道-2026-38</title></programme>
<programme start="20260715090645 +0000" stop="20260715100730 +0000" channel="CCTV3.cn"><title lang="zh">综艺喜乐汇-2026-553</title></programme>
<programme start="20260715100730 +0000" stop="20260715113000 +0000" channel="CCTV3.cn"><title lang="zh">开门大吉-2026-28</title></programme>
<programme start="20260715113000 +0000" stop="20260715125225 +0000" channel="CCTV3.cn"><title lang="zh">越战越勇-2026-28</title></programme>
<programme start="20260715125225 +0000" stop="20260715134925 +0000" channel="CCTV3.cn"><title lang="zh">综艺喜乐汇-2026-601</title></programme>
<programme start="20260715134925 +0000" stop="20260715145430 +0000" channel="CCTV3.cn"><title lang="zh">综艺喜乐汇-2026-476</title></programme>
<programme start="20260715145430 +0000" stop="20260715154030 +0000" channel="CCTV3.cn"><title lang="zh">综艺喜乐汇-2025-486 南来北往13/39</title></programme>
<programme start="20260715154030 +0000" stop="20260715155900 +0000" channel="CCTV3.cn"><title lang="zh">综艺喜乐汇-2025-487 南来北往14/39</title></programme>
<programme start="20260713170000 +0000" stop="20260713173000 +0000" channel="CNBCIndonesia.id"><title lang="id">Economic Update 2026</title></programme>
<programme start="20260713173000 +0000" stop="20260713180000 +0000" channel="CNBCIndonesia.id"><title lang="id">Economic Update 2026</title></programme>
<programme start="20260713180000 +0000" stop="20260713183000 +0000" channel="CNBCIndonesia.id"><title lang="id">Number&apos;s Bite</title></programme>
<programme start="20260713183000 +0000" stop="20260713190000 +0000" channel="CNBCIndonesia.id"><title lang="id">Big Stories Of The Week</title></programme>
<programme start="20260713190000 +0000" stop="20260713193000 +0000" channel="CNBCIndonesia.id"><title lang="id">Insight</title></programme>
<programme start="20260713193000 +0000" stop="20260713200000 +0000" channel="CNBCIndonesia.id"><title lang="id">Insight</title></programme>
<programme start="20260713200000 +0000" stop="20260713203000 +0000" channel="CNBCIndonesia.id"><title lang="id">Cuap Cuap Cuan</title></programme>
<programme start="20260713203000 +0000" stop="20260713210000 +0000" channel="CNBCIndonesia.id"><title lang="id">Cuap Cuap Cuan</title></programme>
<programme start="20260713210000 +0000" stop="20260713230000 +0000" channel="CNBCIndonesia.id"><title lang="id">Closing Bell</title></programme>
<programme start="20260713230000 +0000" stop="20260714003000 +0000" channel="CNBCIndonesia.id"><title lang="id">Evening Up</title></programme>
<programme start="20260714003000 +0000" stop="20260714010000 +0000" channel="CNBCIndonesia.id"><title lang="id">Cuap Cuap Cuan</title></programme>
<programme start="20260714010000 +0000" stop="20260714030000 +0000" channel="CNBCIndonesia.id"><title lang="id">Squawk Box - Live</title></programme>
<programme start="20260714030000 +0000" stop="20260714045500 +0000" channel="CNBCIndonesia.id"><title lang="id">Profit - Live</title></programme>
<programme start="20260714045500 +0000" stop="20260714070000 +0000" channel="CNBCIndonesia.id"><title lang="id">Power Lunch - Live</title></programme>
<programme start="20260714070000 +0000" stop="20260714073000 +0000" channel="CNBCIndonesia.id"><title lang="id">Economic Update 2026</title></programme>
<programme start="20260714073000 +0000" stop="20260714080000 +0000" channel="CNBCIndonesia.id"><title lang="id">Number&apos;s Bite</title></programme>
<programme start="20260714080000 +0000" stop="20260714100000 +0000" channel="CNBCIndonesia.id"><title lang="id">Closing Bell - Live</title></programme>
<programme start="20260714100000 +0000" stop="20260714113000 +0000" channel="CNBCIndonesia.id"><title lang="id">Evening Up - Live</title></programme>
<programme start="20260714113000 +0000" stop="20260714120000 +0000" channel="CNBCIndonesia.id"><title lang="id">Cuap Cuap Cuan</title></programme>
<programme start="20260714120000 +0000" stop="20260714140000 +0000" channel="CNBCIndonesia.id"><title lang="id">Squawk Box</title></programme>
<programme start="20260714140000 +0000" stop="20260714160000 +0000" channel="CNBCIndonesia.id"><title lang="id">Profit</title></programme>
<programme start="20260714160000 +0000" stop="20260714180000 +0000" channel="CNBCIndonesia.id"><title lang="id">Power Lunch</title></programme>
<programme start="20260714180000 +0000" stop="20260714183000 +0000" channel="CNBCIndonesia.id"><title lang="id">Economic Update 2026</title></programme>
<programme start="20260714183000 +0000" stop="20260714190000 +0000" channel="CNBCIndonesia.id"><title lang="id">Number&apos;s Bite</title></programme>
<programme start="20260714190000 +0000" stop="20260714193000 +0000" channel="CNBCIndonesia.id"><title lang="id">Insight</title></programme>
<programme start="20260714193000 +0000" stop="20260714200000 +0000" channel="CNBCIndonesia.id"><title lang="id">Insight</title></programme>
<programme start="20260714200000 +0000" stop="20260714203000 +0000" channel="CNBCIndonesia.id"><title lang="id">Cuap Cuap Cuan</title></programme>
<programme start="20260714203000 +0000" stop="20260714210000 +0000" channel="CNBCIndonesia.id"><title lang="id">Cuap Cuap Cuan</title></programme>
<programme start="20260714210000 +0000" stop="20260714230000 +0000" channel="CNBCIndonesia.id"><title lang="id">Closing Bell</title></programme>
<programme start="20260714230000 +0000" stop="20260715003000 +0000" channel="CNBCIndonesia.id"><title lang="id">Evening Up</title></programme>
<programme start="20260715003000 +0000" stop="20260715010000 +0000" channel="CNBCIndonesia.id"><title lang="id">Cuap Cuap Cuan</title></programme>
<programme start="20260715010000 +0000" stop="20260715030000 +0000" channel="CNBCIndonesia.id"><title lang="id">Squawk Box - Live</title></programme>
<programme start="20260715030000 +0000" stop="20260715045500 +0000" channel="CNBCIndonesia.id"><title lang="id">Profit - Live</title></programme>
<programme start="20260715045500 +0000" stop="20260715070000 +0000" channel="CNBCIndonesia.id"><title lang="id">Power Lunch - Live</title></programme>
<programme start="20260715070000 +0000" stop="20260715093000 +0000" channel="CNBCIndonesia.id"><title lang="id">Financial Forum 2026 - Live</title></programme>
<programme start="20260715093000 +0000" stop="20260715100000 +0000" channel="CNBCIndonesia.id"><title lang="id">Big Stories Of The Week</title></programme>
<programme start="20260715100000 +0000" stop="20260715113000 +0000" channel="CNBCIndonesia.id"><title lang="id">Evening Up - Live</title></programme>
<programme start="20260715113000 +0000" stop="20260715120000 +0000" channel="CNBCIndonesia.id"><title lang="id">Cuap Cuap Cuan</title></programme>
<programme start="20260715120000 +0000" stop="20260715140000 +0000" channel="CNBCIndonesia.id"><title lang="id">Squawk Box</title></programme>
<programme start="20260715140000 +0000" stop="20260715160000 +0000" channel="CNBCIndonesia.id"><title lang="id">Profit</title></programme>
<programme start="20260715160000 +0000" stop="20260715180000 +0000" channel="CNBCIndonesia.id"><title lang="id">Power Lunch</title></programme>
<programme start="20260714004000 +0000" stop="20260714020000 +0000" channel="Friday.ru"><title lang="ru">Секреты на кухне (Зеленый выпуск)</title><desc lang="ru">Камилла Дмитриева сделает авокадо-тост без хлеба. Вадим Абрамов угостит зеленым гаспачо. Николай Гагарин поделится рецептом карпаччо из цукини. А на десерт Нина Тарасова даст соведущим попробовать фруктовый тартар. Вед.: Нина Тарасова, Ольга Вашурина, Вадим Абрамов, Николай Гагарин, Камилла Дмитриева. Россия, 2023, кулинария</desc></programme>
<programme start="20260714020000 +0000" stop="20260714031000 +0000" channel="Friday.ru"><title lang="ru">Секреты на кухне (Гречка)</title><desc lang="ru">Камилла Дмитриева приготовит гречаники. Вадим Абрамов поделится рецептом гречневых блинов. Илья Захаров накормит гречотто с белыми грибами. На десерт Нина Тарасова создаст шоколад из гречишного чая. Вед.: Нина Тарасова, Ольга Вашурина, Вадим Абрамов, Николай Гагарин, Камилла Дмитриева. Россия, 2023, кулинария</desc></programme>
<programme start="20260714031000 +0000" stop="20260714051000 +0000" channel="Friday.ru"><title lang="ru">Битва шефов. 28 с.</title><desc lang="ru">Ренат Агзамов и Константин Ивлев проверят таланты поваров своей команды. Участники приготовят клопсы, мясные пальчики, десерт из слоеных трубочек с белковым кремом и авторское блюдо, основным продуктом которого является рыба. Вед.: Константин Ивлев, Ренат Агзамов. Россия, 2020, кулинария</desc></programme>
<programme start="20260714051000 +0000" stop="20260714073000 +0000" channel="Friday.ru"><title lang="ru">Битва шефов. 29 с.</title><desc lang="ru">Повара представят свои вариации жульена, проявят фантазию в создании пирога блинчатого с мясом и рисом и сладких роллов блинчатых и посоревнуются в приготовлении блюд из страусиных яиц. Вед.: Константин Ивлев, Ренат Агзамов. Россия, 2020, кулинария</desc></programme>
<programme start="20260714073000 +0000" stop="20260714100000 +0000" channel="Friday.ru"><title lang="ru">Молодые ножи. Новая кpoвь. 1 с.</title><desc lang="ru">Константин Ивлев открывает свой кулинарный колледж! Талантливая, но «трудная» молодежь отправится на перевоспитание на кухню. Лучший студент получит работу в мишленовском ресторане и денежный приз. Вед.: Константин Ивлев, Александр Пушков, Илья Захаров. Россия</desc></programme>
<programme start="20260714100000 +0000" stop="20260714113000 +0000" channel="Friday.ru"><title lang="ru">Молодые ножи (Сэндвичи)</title><desc lang="ru">Константин Ивлев предложит участникам разгадать кулинарный детектив и приготовить блюдо средиземноморской кухни. Во втором испытании поварам предстоит создать креативное блюдо из любых 4 продуктов. А финалисты поработают с цветками цукини. Вед.: Константин Ивлев. Россия, 2021, шоу талантов, кулинария</desc></programme>
<programme start="20260714113000 +0000" stop="20260714124000 +0000" channel="Friday.ru"><title lang="ru">Молодые ножи (Именитые шефы)</title><desc lang="ru">В специальном выпуске кулинарного поединка сойдутся именитые шефы. Им предстоит угадать блюда советской ресторанной классики и подать их в новой интерпретации. Вед.: Константин Ивлев. Россия, 2021, шоу талантов, кулинария</desc></programme>
<programme start="20260714124000 +0000" stop="20260714140000 +0000" channel="Friday.ru"><title lang="ru">Молодые ножи (Роскошь советской кулинарии)</title><desc lang="ru">Участникам предстоит приготовить классические советские блюда, показать умение соединять ингредиенты и сделать для финальной дегустации блюдо с майонезом. Вместе с Константином Ивлевым выбирать победителя будет Алексей Глызин. Вед.: Константин Ивлев. Россия, 2021, шоу талантов, кулинария</desc></programme>
<programme start="20260714140000 +0000" stop="20260714150000 +0000" channel="Friday.ru"><title lang="ru">Черный список. На кухне (Екатеринбург. Кондитория)</title><desc lang="ru">Александр Пушков и Илья Захаров отправятся в Екатеринбург. Здесь помощь понадобилась заведению «Кондитория», который остался без шеф-повара. Пройдут ли кандидаты на должность все проверки, подготовленные ведущими? Вед.: Алексей Земсков, Ренат Агзамов, Дмитрий Масленников, Дмитрий Губерниев, Александр Пушков. Россия, 2019, развлечения</desc></programme>
<programme start="20260714150000 +0000" stop="20260714160000 +0000" channel="Friday.ru"><title lang="ru">Черный список. На кухне (Санкт-Петербург. Ланселот)</title><desc lang="ru">Помощь в поиске шеф-повара понадобилась ресторану европейской кухни «Ланселот», расположенному в Санкт-Петербурге. Вед.: Алексей Земсков, Ренат Агзамов, Дмитрий Масленников, Дмитрий Губерниев, Александр Пушков. Россия, 2019, развлечения</desc></programme>
<programme start="20260714160000 +0000" stop="20260714170000 +0000" channel="Friday.ru"><title lang="ru">Новый Ревизорро (Телекинез. Церемония Камбо)</title><desc lang="ru">Съемочная группа отправляется на секретное задание, чтобы разоблачить мошенников. Под прицелом видеокамер находятся ветеринарные и косметологические клиники, автосервисы и даже экстрасенсы, маги и шаманы. В ходе журналистского расследования проводятся необходимые экспертизы, а за услугами обращаются тайные покупатели. Россия</desc></programme>
<programme start="20260714170000 +0000" stop="20260714182000 +0000" channel="Friday.ru"><title lang="ru">Новый Ревизорро. 4 с.</title><desc lang="ru">К каким методам похудения прибегают люди? Насколько эти методы являются эффективными и безопасными? Кто зарабатывает на желании похудеть? И все ли специалисты, которые предлагают сбросить лишние килограммы, соблюдают законы? Россия</desc></programme>
<programme start="20260714182000 +0000" stop="20260714192000 +0000" channel="Friday.ru"><title lang="ru">Черный список. На кухне (Официанты)</title><desc lang="ru">Менеджер сети ресторанов в Москве обратилась к Александру Пушкову и Илье Захарову с нестандартной для ведущих просьбой – найти официанта. Илья и Александр проверят кандидатов из трех ценовых сегментов в стрессовых условиях. Вед.: Алексей Земсков, Ренат Агзамов, Дмитрий Масленников, Дмитрий Губерниев, Александр Пушков. Россия, 2019, развлечения</desc></programme>
<programme start="20260714192000 +0000" stop="20260714200000 +0000" channel="Friday.ru"><title lang="ru">Черный список. На кухне (Москва. Стамбул Сити)</title><desc lang="ru">Илья и Александр заглянут в ресторан «Стамбул Сити» в Москве. Он специализируется на восточной кухне. Ведущие оценят работу трех шеф-поваров: каждый приготовит традиционное восточное блюдо. Вед.: Алексей Земсков, Ренат Агзамов, Дмитрий Масленников, Дмитрий Губерниев, Александр Пушков. Россия, 2019, развлечения</desc></programme>
<programme start="20260714200000 +0000" stop="20260714214000 +0000" channel="Friday.ru"><title lang="ru">Ставка на любовь. 8 с.</title><desc lang="ru">Экстремальное реалити, где звездные пары проверяют силу своих чувств. По правилам проекта участники проходят испытания и ставят «ставки» на своих партнеров: справятся они или нет. Те, кто отгадают исход испытаний, получают иммунитет, а не угадавшие номинируются на голосовании. Выиграет только одна пара и получит денежный приз. Реж.: Михаил Полиит. Вед.: Регина Тодоренко, Влад Топалов. Россия</desc></programme>
<programme start="20260714214000 +0000" stop="20260714222000 +0000" channel="Friday.ru"><title lang="ru">Пятница News. 117 с.</title><desc lang="ru">В основе шоу – блиц-опросы, звездные гости, интервью, репортажи и, как следует из названия, самые свежие новости российского шоу-бизнеса. Шоу для тех, кто хочет быть в курсе всех событий в мире музыки, кино, соцсетей, искусства и технологий. Каждый выпуск длится всего полчаса, но содержит массу интересной информации. Вед.: Игорь Лантратов, Ольга Благодарская. Россия</desc></programme>
<programme start="20260714222000 +0000" stop="20260714231000 +0000" channel="Friday.ru"><title lang="ru">т/с Комиссар Рекс (Амок)</title><desc lang="ru">Штефан Ланц, узнав что он ВИЧ-инфицирован, стал убивать всех, с кем у него были отношения. Мозер пытается остановить серию убийств. Ведь ко всему прочему Ланц не знает, что поставленный ему диагноз ошибочен. Реж.: Ганс Вернер, Оливер Хиршбигель, Михаэль Рибль. В ролях: Тобиас Моретти, Гедеон Буркхард, Герхард Земан, Хайнц Вайксельбраун, Вольф Бахофнер, Ретт Батлер, Мартин Вайнек, Санто фон Хаус Цигельмайер, Фриц Муляр, Александр Пшилль. Германия, Австрия, 1994-2004, боевик, криминал, детектив</desc></programme>
<programme start="20260714231000 +0000" stop="20260715000000 +0000" channel="Friday.ru"><title lang="ru">т/с Комиссар Рекс (Золотая медаль)</title><desc lang="ru">Маленькая девочка Рената Вагнер найдена мертвой после посещения фортепианного концерта. Вскоре после этого происходит убийство пианистки Кристы Штробль. Мозеру приходится действовать быстро, чтобы предотвратить очередное убийство. Реж.: Ганс Вернер, Оливер Хиршбигель, Михаэль Рибль. В ролях: Тобиас Моретти, Гедеон Буркхард, Герхард Земан, Хайнц Вайксельбраун, Вольф Бахофнер, Ретт Батлер, Мартин Вайнек, Санто фон Хаус Цигельмайер, Фриц Муляр, Александр Пшилль. Германия, Австрия, 1994-2004, боевик, криминал, детектив</desc></programme>
<programme start="20260715000000 +0000" stop="20260715005000 +0000" channel="Friday.ru"><title lang="ru">На ножах (Солнечногорск. Царский)</title><desc lang="ru">Константин Ивлев приехал в Солнечногорск, чтобы помочь ресторану «Царский». Когда-то это была столовая военных, которая позже превратилась в самый лучший ресторан в городе. Всего несколько лет назад попасть в него было непросто. Вед.: Константин Ивлев. Россия, 2016-2024, реалити-шоу, кулинария</desc></programme>
<programme start="20260715005000 +0000" stop="20260715020000 +0000" channel="Friday.ru"><title lang="ru">Секреты на кухне. 16 с.</title><desc lang="ru">Камилла Дмитриева сделает салат с крабовыми палочками и грейпфрутом. Илья Захаров угостит севиче с креветками и апельсином. Нина Тарасова даст рецепт цитрусового крем-брюле. Вадим Абрамов будет удивлять морковным супом с мандаринами. Вед.: Нина Тарасова, Ольга Вашурина, Вадим Абрамов, Николай Гагарин, Камилла Дмитриева. Россия, 2023, кулинария</desc></programme>
<programme start="20260715020000 +0000" stop="20260715024000 +0000" channel="Friday.ru"><title lang="ru">Секреты на кухне (Рыба)</title><desc lang="ru">Вадим Абрамов расскажет, что такое брандада из трески. Ольга Вашурина сделает закусочные шарики. Николай Гагарин приготовит палтуса со спаржей и лисичками. А Нина Тарасова даст соведущим попробовать профитроли с начинкой из лосося. Вед.: Нина Тарасова, Ольга Вашурина, Вадим Абрамов, Николай Гагарин, Камилла Дмитриева. Россия, 2023, кулинария</desc></programme>
<programme start="20260715024000 +0000" stop="20260715030000 +0000" channel="Friday.ru"><title lang="ru">Пятница News. 117 с.</title><desc lang="ru">В основе шоу – блиц-опросы, звездные гости, интервью, репортажи и, как следует из названия, самые свежие новости российского шоу-бизнеса. Шоу для тех, кто хочет быть в курсе всех событий в мире музыки, кино, соцсетей, искусства и технологий. Каждый выпуск длится всего полчаса, но содержит массу интересной информации. Вед.: Игорь Лантратов, Ольга Благодарская. Россия</desc></programme>
<programme start="20260715030000 +0000" stop="20260715035000 +0000" channel="Friday.ru"><title lang="ru">Гастротур (Смоленск)</title><desc lang="ru">В Смоленске Дмитрий Левицкий разгадает секреты местных блюд. Он выяснит, как из гречки получить смоленскую крупу, приготовит картофельный талалуй, попробует смоленские кундюмы и лапуны, сходит на грибную охоту и узнает все о космической еде. Вед.: Дмитрий Левицкий, Александр Пушков. Россия, 2021, кулинария, шоу о путешествиях</desc></programme>
<programme start="20260715035000 +0000" stop="20260715053000 +0000" channel="Friday.ru"><title lang="ru">Четыре дачи (Приморский край)</title><desc lang="ru">Елена будет ждать участников на своей «мелодичной даче». Анна проведет экскурсию по даче «приморское изобилие». Наталья удивит «морским экстримом», а Анна покажет дачу в стиле джапанди. Россия, 2022, реалити-шоу</desc></programme>
<programme start="20260715053000 +0000" stop="20260715073000 +0000" channel="Friday.ru"><title lang="ru">Четыре дачи (Волгоградская область)</title><desc lang="ru">Екатерина покажет свою семейную дачу с большим количеством ягод. Ольга расскажет, какая дача для нее является «самой настоящей». Дарья будет удивлять своей «продуманной» дачей. А Анастасия пригласит на «многогранную» дачу. Россия, 2022, реалити-шоу</desc></programme>
<programme start="20260715073000 +0000" stop="20260715103000 +0000" channel="Friday.ru"><title lang="ru">Молодые ножи. Новая кpoвь. 2 с.</title><desc lang="ru">Ученики Константина Ивлева отправляются на первое занятие в кулинарной академии, которое пройдет на птицефабрике. Полученные знания студенты смогут применить во время сдачи экзамена. Вед.: Константин Ивлев, Александр Пушков, Илья Захаров. Россия</desc></programme>
<programme start="20260715103000 +0000" stop="20260715110000 +0000" channel="Friday.ru"><title lang="ru">Домохозяйки против кондитеров. 6 с.</title><desc lang="ru">Кулинарное шоу, в котором домохозяйки соревнуются с профессиональными кондитерами. В программе происходит батл между командами: с одной стороны – домохозяйки, с другой – профессиональные кондитеры. Задача участников – приготовить десерты, а жюри оценивает их вкус и внешний вид</desc></programme>
<programme start="20260715110000 +0000" stop="20260715121000 +0000" channel="Friday.ru"><title lang="ru">На ножах (Москва. Баклажан)</title><desc lang="ru">Кафе «Баклажан» в Москве много лет радовало посетителей своей кухней. Но из заведения ушел опытный повар, и с приготовлением блюд возникли проблемы. Коллективу «Баклажана» потребовался совет Константина Ивлева. Вед.: Константин Ивлев. Россия, 2016-2024, реалити-шоу, кулинария</desc></programme>
<programme start="20260715121000 +0000" stop="20260715144000 +0000" channel="Friday.ru"><title lang="ru">На ножах (Щелково. Гостеев)</title><desc lang="ru">Константина Ивлева попросили о помощи сотрудники комплекса «Гостеев», который расположен в Щелково. В ресторане комплекса нет повара, а его работу выполняют непрофессионалы. Вед.: Константин Ивлев. Россия, 2016-2024, реалити-шоу, кулинария</desc></programme>
<programme start="20260715144000 +0000" stop="20260715153000 +0000" channel="Friday.ru"><title lang="ru">На ножах (Подольск. Панорама Лаунж)</title><desc lang="ru">В ресторане «Панорама Лаунж» в Подольске Константин Ивлев столкнется со слишком самоуверенным шеф-поваром, слабым сервисом и неграмотным управлением. Захочет ли Константин помогать команде? Вед.: Константин Ивлев. Россия, 2016-2024, реалити-шоу, кулинария</desc></programme>
<programme start="20260715153000 +0000" stop="20260715160000 +0000" channel="Friday.ru"><title lang="ru">На ножах (Краснодар. Иерусалим)</title><desc lang="ru">Владельцы кафе «Иерусалим» в Краснодаре не сомневаются в своих кулинарных способностях. Им хотелось бы популяризировать арабскую кухню в своем городе. Но местные жители не так часто заходят в кафе. Вед.: Константин Ивлев. Россия, 2016-2024, реалити-шоу, кулинария</desc></programme>
<programme start="20260715160000 +0000" stop="20260715180000 +0000" channel="Friday.ru"><title lang="ru">Черный список. На кухне (Екатеринбург. Admiral)</title><desc lang="ru">В Екатеринбурге Александр Пушков и Илья Захаров будут искать шеф-повара для ресторана «Admiral» средиземноморской кухни. Ведущие выберут специалистов из трех ценовых сегментов и проверят их умение готовить классические блюда Средиземноморья. Вед.: Алексей Земсков, Ренат Агзамов, Дмитрий Масленников, Дмитрий Губерниев, Александр Пушков. Россия, 2019, развлечения</desc></programme>
<programme start="20260715180000 +0000" stop="20260715190000 +0000" channel="Friday.ru"><title lang="ru">Черный список. На кухне (Москва. Heavy Haze)</title><desc lang="ru">Александр Пушков и Илья Захаров отправятся в бар «Heavy Haze», который расположен в Москве. Ведущим предстоит найти шеф-повара, который способен справиться с паназиатским меню с уклоном во вьетнамскую кухню. Вед.: Алексей Земсков, Ренат Агзамов, Дмитрий Масленников, Дмитрий Губерниев, Александр Пушков. Россия, 2019, развлечения</desc></programme>
<programme start="20260715190000 +0000" stop="20260715200000 +0000" channel="Friday.ru"><title lang="ru">Черный список. На кухне (Санкт-Петербург. Ланселот)</title><desc lang="ru">Помощь в поиске шеф-повара понадобилась ресторану европейской кухни «Ланселот», расположенному в Санкт-Петербурге. Вед.: Алексей Земсков, Ренат Агзамов, Дмитрий Масленников, Дмитрий Губерниев, Александр Пушков. Россия, 2019, развлечения</desc></programme>
<programme start="20260715200000 +0000" stop="20260715215000 +0000" channel="Friday.ru"><title lang="ru">Ставка на любовь. 9 с.</title><desc lang="ru">Экстремальное реалити, где звездные пары проверяют силу своих чувств. По правилам проекта участники проходят испытания и ставят «ставки» на своих партнеров: справятся они или нет. Те, кто отгадают исход испытаний, получают иммунитет, а не угадавшие номинируются на голосовании. Выиграет только одна пара и получит денежный приз. Реж.: Михаил Полиит. Вед.: Регина Тодоренко, Влад Топалов. Россия</desc></programme>
<programme start="20260715215000 +0000" stop="20260715221500 +0000" channel="Friday.ru"><title lang="ru">Пятница News. 119 с.</title><desc lang="ru">В основе шоу – блиц-опросы, звездные гости, интервью, репортажи и, как следует из названия, самые свежие новости российского шоу-бизнеса. Шоу для тех, кто хочет быть в курсе всех событий в мире музыки, кино, соцсетей, искусства и технологий. Каждый выпуск длится всего полчаса, но содержит массу интересной информации. Вед.: Игорь Лантратов, Ольга Благодарская. Россия</desc></programme>
<programme start="20260715221500 +0000" stop="20260715222000 +0000" channel="Friday.ru"><title lang="ru">Ставка на любовь. 9 с.</title><desc lang="ru">Экстремальное реалити, где звездные пары проверяют силу своих чувств. По правилам проекта участники проходят испытания и ставят «ставки» на своих партнеров: справятся они или нет. Те, кто отгадают исход испытаний, получают иммунитет, а не угадавшие номинируются на голосовании. Выиграет только одна пара и получит денежный приз. Реж.: Михаил Полиит. Вед.: Регина Тодоренко, Влад Топалов. Россия</desc></programme>
<programme start="20260715222000 +0000" stop="20260715230000 +0000" channel="Friday.ru"><title lang="ru">т/с Комиссар Рекс (Мишки-убийцы)</title><desc lang="ru">В витрине игрушечного магазина взрывается игрушечный медвежонок. Штокингер и Хеллерер пытаются выяснить, с какой целью в игрушку установили взрывное устройство. Мозер в это время лежит дома из-за перелома ноги, но тоже участвует в расследовании. Реж.: Ганс Вернер, Оливер Хиршбигель, Михаэль Рибль. В ролях: Тобиас Моретти, Гедеон Буркхард, Герхард Земан, Хайнц Вайксельбраун, Вольф Бахофнер, Ретт Батлер, Мартин Вайнек, Санто фон Хаус Цигельмайер, Фриц Муляр, Александр Пшилль. Германия, Австрия, 1994-2004, боевик, криминал, детектив</desc></programme>
<programme start="20260715230000 +0000" stop="20260715235000 +0000" channel="Friday.ru"><title lang="ru">т/с Комиссар Рекс (Принеси мне череп Бетховена)</title><desc lang="ru">Ночью с городского кладбища двое воров крадут череп Людвига ван Бетховена. Мозеру необходимо найти украденный череп, выяснить, зачем он был нужен ворам. В скором времени происходит убийство одного из похитителей черепа. Реж.: Ганс Вернер, Оливер Хиршбигель, Михаэль Рибль. В ролях: Тобиас Моретти, Гедеон Буркхард, Герхард Земан, Хайнц Вайксельбраун, Вольф Бахофнер, Ретт Батлер, Мартин Вайнек, Санто фон Хаус Цигельмайер, Фриц Муляр, Александр Пшилль. Германия, Австрия, 1994-2004, боевик, криминал, детектив</desc></programme>
<programme start="20260715235000 +0000" stop="20260716004000 +0000" channel="Friday.ru"><title lang="ru">На ножах (Павловский Посад. Катана)</title><desc lang="ru">Сегодня терпеливый мастер доведет до ума самое убыточное заведение Павловского Посада. Обладатель тяжелой руки и адепт шоковой терапии рубит с плеча и делает фарш из всех, кто отказывается понимать с первого раза. Но результат того стоит! Вед.: Константин Ивлев. Россия, 2016-2024, реалити-шоу, кулинария</desc></programme>
</tv>